{
    "__default__" :
    {
        "walltime" : "walltime=04:00:00",
        "cores" : "nodes=1:ppn=1",
        "memory" : "mem=20GB"
    },
    "init_object":
    {
        "walltime" : "walltime=12:00:00",
        "cores" : "nodes=1:ppn=2",
        "memory" : "mem=40GB"
    },
    "components":
    {
        "walltime" : "walltime=08:00:00",
        "cores" : "nodes=1:ppn=2",
        "memory" : "mem=40GB"
    },
    "markers":
    {
        "walltime" : "walltime=08:00:00",
        "cores" : "nodes=1:ppn=2",
        "memory" : "mem=40GB"
    }
}
